djangoPolyglot/__init__.py
djangoPolyglot/admin.py
djangoPolyglot/apps.py
djangoPolyglot/models.py
djangoPolyglot/tests.py
djangoPolyglot/views.py
djangoPolyglot/management/__init__.py
djangoPolyglot/management/commands/__init__.py
djangoPolyglot/management/commands/arguments.py
djangoPolyglot/management/commands/django-polyglot.py
djangoPolyglot/management/commands/license.py
django_polyglot_translator-1.2.2.dist-info/LICENSE
django_polyglot_translator-1.2.2.dist-info/METADATA
django_polyglot_translator-1.2.2.dist-info/WHEEL
django_polyglot_translator-1.2.2.dist-info/top_level.txt
django_polyglot_translator-1.2.2.dist-info/RECORD
