Metadata-Version: 2.1
Name: django-polyglot-translator
Version: 1.2.2
Summary: Polyglot integration for Django Web Framework
Home-page: https://github.com/riccardoFasan/django-polyglot
Author: Riccardo Fasan
Author-email: fasanriccardo21@gmail.com
License: MIT
Project-URL: BugTracker, https://github.com/riccardoFasan/django-polyglot/issues
Project-URL: Homepage, https://github.com/riccardoFasan/django-polyglot
Classifier: Programming Language :: Python :: 3.10
Classifier: License :: OSI Approved :: MIT License
Classifier: Operating System :: OS Independent
Requires-Python: >=3.8
License-File: LICENSE
Requires-Dist: Django (>3.2)
Requires-Dist: polyglot-translator (>=2.2.3)
